Metadata-Version: 2.1
Name: maestro-client
Version: 0.7.4
Summary: Maestro client in python
Home-page: https://github.com/owlint/maestro-python-client
Author: Laurent Evrard
Author-email: evrardlaurent77@gmail.com
License: WTFPL
Platform: UNKNOWN
Classifier: Programming Language :: Python
Classifier: Development Status :: 1 - Planning
Classifier: License :: OSI Approved
Classifier: Natural Language :: French
Classifier: Operating System :: OS Independent
Classifier: Programming Language :: Python :: 3.6
Classifier: Topic :: Communications
